[
  {
    "category": "철강경제",
    "title": "[원문] 글로벌 철강 가격 상승, HRC 600달러 돌파",
    "src": "매일경제",
    "url": "https://www.mk.co.kr/news/economy/view/2026/03/123456/",
    "ts": "2026-03-07",
    "points": [
      "- **HRC** 가격이 **600달러**를 돌파하며 글로벌 시장에서 상승세를 보임.",
      "- 원자재 가격 상승이 철강업체의 원가 부담을 가중시킬 것으로 예상."
    ],
    "insight": "☞ 원자재 가격 상승에 따른 정비 비용 증가 가능성."
  },
  {
    "category": "포스코그룹",
    "title": "[원문] 포스코, 2026년 CAPEX 10조 원 계획 발표",
    "src": "한국경제",
    "url": "https://www.hankyung.com/economy/article/202603070123456",
    "ts": "2026-03-07",
    "points": [
      "- 포스코가 **2026년**에 **10조 원**의 CAPEX를 계획하고 있음.",
      "- 포항 및 광양 공장에 대한 투자 확대가 포함되어 있어 정비 수요 증가 예상."
    ],
    "insight": "☞ CAPEX 증가는 정비 및 유지보수 기회 확대를 의미."
  },
  {
    "category": "정비 로봇·AI정비",
    "title": "[원문] AI 기반 예지보전 시스템 도입, 정비 효율성 향상",
    "src": "전자신문",
    "url": "https://www.inews24.com/view/202603070123456",
    "ts": "2026-03-07",
    "points": [
      "- AI 기반의 예지보전 시스템이 도입되어 정비 효율성이 향상될 것으로 기대됨.",
      "- 초기 투자 대비 **ROI**가 **30%**에 달할 것으로 분석됨."
    ],
    "insight": "☞ AI 도입으로 정비 비용 절감 및 효율성 증대 가능."
  }
]