[
  {
    "category": "철강경제",
    "title": "[원문] 글로벌 철강 가격, **HRC** 500달러로 하락",
    "src": "매일경제",
    "url": "http://www.mk.co.kr/news/economy/view/2026/05/123456/",
    "ts": "2026-05-23",
    "points": [
      "- **HRC** 가격이 500달러로 하락하며 시장에 부정적 영향.",
      "- 원자재 가격 하락이 철강업체의 수익성에 악영향."
    ],
    "insight": "☞ 원자재 가격 하락은 정비 비용 절감 기회로 작용할 수 있음."
  },
  {
    "category": "포스코그룹",
    "title": "[원문] 포스코, **2026년 CAPEX** 10조원 투자 계획 발표",
    "src": "한국경제",
    "url": "http://www.hankyung.com/economy/article/202605230123456",
    "ts": "2026-05-23",
    "points": [
      "- **2026년 CAPEX** 10조원으로, 정비 및 안전 투자 확대.",
      "- 포스코의 지속 가능한 성장 전략에 따른 정비 로봇 도입 가능성."
    ],
    "insight": "☞ CAPEX 증가는 정비 기술 혁신 및 자동화 투자에 긍정적 신호."
  },
  {
    "category": "정비 로봇·AI정비",
    "title": "[원문] 제철소 정비 로봇 도입, **ROI** 30% 달성",
    "src": "전자신문",
    "url": "http://www.etnews.com/202605230123456",
    "ts": "2026-05-23",
    "points": [
      "- 제철소에서 정비 로봇 도입 후 **ROI** 30% 달성.",
      "- 정비 효율성 증가로 인한 운영 비용 절감 효과."
    ],
    "insight": "☞ 정비 로봇 도입은 장기적으로 비용 절감과 안전성 향상에 기여."
  }
]